LICENSE
MANIFEST.in
README.ja.rst
README.rst
setup.cfg
setup.py
pumblr/__init__.py
pumblr/api.py
pumblr/errors.py
pumblr/models.py
pumblr/utils.py
pumblr.egg-info/PKG-INFO
pumblr.egg-info/SOURCES.txt
pumblr.egg-info/dependency_links.txt
pumblr.egg-info/entry_points.txt
pumblr.egg-info/not-zip-safe
pumblr.egg-info/top_level.txt
testdata/dashboard.json
testdata/error.xhtml
testdata/like
testdata/read.json
testdata/unlike