Metadata-Version: 1.0
Name: pumblr
Version: 0.1.2dev
Summary: A python library for The Tumblr API.
Home-page: http://d.hatena.ne.jp/se-kichi
Author: seikichi
Author-email: seikichi@kmc.gr.jp
License: MIT
Keywords: tumblr
Platform: UNKNOWN
Classifier: Development Status :: 3 - Alpha
Classifier: Intended Audience :: Developers
Classifier: License :: OSI Approved :: MIT License
Classifier: Programming Language :: Python
